MANIFEST.in
README.md
setup.py
cellworld_tlppo/README.md
cellworld_tlppo/__init__.py
cellworld_tlppo/graph.py
cellworld_tlppo/license.txt
cellworld_tlppo/mcts.py
cellworld_tlppo/resources.py
cellworld_tlppo/setup.cfg
cellworld_tlppo/state.py
cellworld_tlppo/steps.py
cellworld_tlppo/tlppo.py
cellworld_tlppo/tlppo_learner.py
cellworld_tlppo/tlppo_tester.py
cellworld_tlppo.egg-info/PKG-INFO
cellworld_tlppo.egg-info/SOURCES.txt
cellworld_tlppo.egg-info/dependency_links.txt
cellworld_tlppo.egg-info/not-zip-safe
cellworld_tlppo.egg-info/requires.txt
cellworld_tlppo.egg-info/top_level.txt
cellworld_tlppo/__pycache__/__init__.cpython-312.pyc
cellworld_tlppo/__pycache__/graph.cpython-312.pyc
cellworld_tlppo/__pycache__/mcts.cpython-312.pyc
cellworld_tlppo/__pycache__/state.cpython-312.pyc
cellworld_tlppo/__pycache__/steps.cpython-312.pyc
cellworld_tlppo/__pycache__/tlppo.cpython-312.pyc
cellworld_tlppo/__pycache__/tlppo_learner.cpython-312.pyc
cellworld_tlppo/__pycache__/tlppo_tester.cpython-312.pyc
cellworld_tlppo/belief_state/__init__.py
cellworld_tlppo/belief_state/belief_state.py
cellworld_tlppo/belief_state/belief_state_component.py
cellworld_tlppo/belief_state/directed_difusion_component.py
cellworld_tlppo/belief_state/gaussian_diffusion_component.py
cellworld_tlppo/belief_state/utils.py
cellworld_tlppo/belief_state/__pycache__/__init__.cpython-312.pyc
cellworld_tlppo/belief_state/__pycache__/belief_state.cpython-312.pyc
cellworld_tlppo/belief_state/__pycache__/belief_state_component.cpython-312.pyc
cellworld_tlppo/belief_state/__pycache__/directed_difusion_component.cpython-312.pyc
cellworld_tlppo/belief_state/__pycache__/gaussian_diffusion_component.cpython-312.pyc
cellworld_tlppo/belief_state/__pycache__/utils.cpython-312.pyc