Metadata-Version: 2.1
Name: cellworld_tlppo
Version: 0.0.15
Author: German Espinosa
Author-email: germanespinosa@gmail.com
License: MIT
Requires-Dist: cellworld_game
Requires-Dist: cellworld_gym
Requires-Dist: scikit-learn
